seo_optimizer/__init__.py
seo_optimizer/analytics.py
seo_optimizer/apps.py
seo_optimizer/async_utils.py
seo_optimizer/base.py
seo_optimizer/exceptions.py
seo_optimizer/fields.py
seo_optimizer/i18n.py
seo_optimizer/mobile.py
seo_optimizer/models.py
seo_optimizer/redirects.py
seo_optimizer/signals.py
seo_optimizer/sitemaps.py
seo_optimizer/utils.py
seo_optimizer/version.py
seo_optimizer/locale/en/LC_MESSAGES/django.po
seo_optimizer/templates/seo_optimizer/hreflang.html
seo_optimizer/templates/seo_optimizer/mobile_meta.html
seo_optimizer/templatetags/i18n_seo_tags.py
seo_optimizer/templatetags/mobile_seo_tags.py
seo_optimizer/templatetags/seo_tags.py
django_seo_optimizer-1.0.1.dist-info/METADATA
django_seo_optimizer-1.0.1.dist-info/WHEEL
django_seo_optimizer-1.0.1.dist-info/licenses/LICENSE
django_seo_optimizer-1.0.1.dist-info/RECORD
