Metadata-Version: 2.4
Name: django-seo-optimizer
Version: 1.0.1
Summary: A powerful Django SEO optimization package with modern features
Project-URL: Homepage, https://github.com/avixiii-dev/django-seo-optimizer
Project-URL: Documentation, https://avixiii.com/django-seo-optimizer
Project-URL: Bug Tracker, https://github.com/avixiii-dev/django-seo-optimizer/issues
Author-email: avixiii <contact@avixiii.com>
License-File: LICENSE
Classifier: Development Status :: 5 - Production/Stable
Classifier: Framework :: Django
Classifier: Framework :: Django :: 3.2
Classifier: Framework :: Django :: 4.0
Classifier: Framework :: Django :: 4.1
Classifier: Framework :: Django :: 4.2
Classifier: Framework :: Django :: 5.0
Classifier: Intended Audience :: Developers
Classifier: License :: OSI Approved :: MIT License
Classifier: Operating System :: OS Independent
Classifier: Programming Language :: Python :: 3
Classifier: Programming Language :: Python :: 3.8
Classifier: Programming Language :: Python :: 3.9
Classifier: Programming Language :: Python :: 3.10
Classifier: Programming Language :: Python :: 3.11
Classifier: Topic :: Internet :: WWW/HTTP :: Site Management
Classifier: Topic :: Internet :: WWW/HTTP :: Site Management :: Link Checking
Requires-Python: >=3.8
Requires-Dist: beautifulsoup4>=4.12.0
Requires-Dist: django>=3.2
Requires-Dist: python-slugify>=8.0.1
Requires-Dist: requests>=2.31.0
